py_buycoins/APIClient.py
py_buycoins/__init__.py
py_buycoins/exc.py
py_buycoins/naira_token_account.py
py_buycoins/orders.py
py_buycoins/p2p.py
py_buycoins/receive.py
py_buycoins/sending.py
py_buycoins/gcore/__init__.py
py_buycoins/gcore/mutations.py
py_buycoins/gcore/queries.py
py_buycoins-0.1.1.dist-info/LICENSE.txt
py_buycoins-0.1.1.dist-info/METADATA
py_buycoins-0.1.1.dist-info/WHEEL
py_buycoins-0.1.1.dist-info/top_level.txt
py_buycoins-0.1.1.dist-info/RECORD
