Metadata-Version: 2.1
Name: py-buycoins
Version: 0.1.1
Summary: Python client library for BuyCoins Africa API
Home-page: https://github.com/Bashorun97/BuyCoins-Python-SDK
Author: Paul <paulcurious7@gmail.com>, Emmanuel Bashorun <bashorun.emma@gmail.com>
License: UNKNOWN
Platform: UNKNOWN
Classifier: Development Status :: 3 - Alpha
Classifier: Intended Audience :: Developers
Classifier: Topic :: Software Development :: Build Tools
Classifier: Operating System :: OS Independent
Classifier: License :: OSI Approved :: MIT License
Classifier: Programming Language :: Python :: 3.5
Classifier: Programming Language :: Python :: 3.6
Classifier: Programming Language :: Python :: 3.7
Classifier: Programming Language :: Python :: 3.8
Requires-Python: >=3
Requires-Dist: requests
